{"timeToUse": ["2023-09-21 04:00:00+02:00", "2023-09-21 05:00:00+02:00", "2023-09-21 06:00:00+02:00", "2023-09-21 07:00:00+02:00", "2023-09-21 08:00:00+02:00", "2023-09-21 09:00:00+02:00", "2023-09-21 10:00:00+02:00", "2023-09-21 11:00:00+02:00", "2023-09-21 12:00:00+02:00", "2023-09-21 13:00:00+02:00", "2023-09-21 14:00:00+02:00", "2023-09-21 15:00:00+02:00", "2023-09-21 16:00:00+02:00"], "23": {"background-color": "#C41E3A", "icon": "off", "msg": "Vent. Prisen er 70 \u00f8re/kWh."}, "22": {"background-color": "#C41E3A", "icon": "off", "msg": "Vent. Prisen er 74 \u00f8re/kWh."}, "21": {"background-color": "#C41E3A", "icon": "off", "msg": "Vent. Prisen er 85 \u00f8re/kWh."}, "20": {"background-color": "#C41E3A", "icon": "off", "msg": "Vent. Prisen er 115 \u00f8re/kWh."}, "19": {"background-color": "#C41E3A", "icon": "off", "msg": "Vent. Prisen er 204 \u00f8re/kWh."}, "18": {"background-color": "#C41E3A", "icon": "off", "msg": "Vent. Prisen er 146 \u00f8re/kWh."}, "17": {"background-color": "#C41E3A", "icon": "off", "msg": "Vent. Prisen er 92 \u00f8re/kWh."}, "16": {"background-color": "#28A76F", "icon": "on", "msg": "T\u00e6nd. Prisen er 39 \u00f8re/kWh."}, "15": {"background-color": "#28A76F", "icon": "on", "msg": "T\u00e6nd. Prisen er 1 \u00f8re/kWh."}, "14": {"background-color": "#28A76F", "icon": "on", "msg": "T\u00e6nd. Prisen er 0 \u00f8re/kWh."}, "13": {"background-color": "#28A76F", "icon": "on", "msg": "T\u00e6nd. Prisen er 1 \u00f8re/kWh."}, "12": {"background-color": "#28A76F", "icon": "on", "msg": "T\u00e6nd. Prisen er 1 \u00f8re/kWh."}, "11": {"background-color": "#28A76F", "icon": "on", "msg": "T\u00e6nd. Prisen er 1 \u00f8re/kWh."}, "10": {"background-color": "#28A76F", "icon": "on", "msg": "T\u00e6nd. Prisen er 1 \u00f8re/kWh."}, "9": {"background-color": "#28A76F", "icon": "on", "msg": "T\u00e6nd. Prisen er 2 \u00f8re/kWh."}, "8": {"background-color": "#28A76F", "icon": "on", "msg": "T\u00e6nd. Prisen er 3 \u00f8re/kWh."}, "7": {"background-color": "#28A76F", "icon": "on", "msg": "T\u00e6nd. Prisen er 2 \u00f8re/kWh."}, "6": {"background-color": "#28A76F", "icon": "on", "msg": "T\u00e6nd. Prisen er 1 \u00f8re/kWh."}, "5": {"background-color": "#28A76F", "icon": "on", "msg": "T\u00e6nd. Prisen er 0 \u00f8re/kWh."}, "4": {"background-color": "#28A76F", "icon": "on", "msg": "T\u00e6nd. Prisen er 0 \u00f8re/kWh."}}